mcp_testmind/__init__.py
mcp_testmind/__main__.py
mcp_testmind/server.py
mcp_testmind-0.1.0.dist-info/METADATA
mcp_testmind-0.1.0.dist-info/WHEEL
mcp_testmind-0.1.0.dist-info/entry_points.txt
mcp_testmind-0.1.0.dist-info/top_level.txt
mcp_testmind-0.1.0.dist-info/RECORD
