Metadata-Version: 2.4
Name: mcp-testmind
Version: 0.1.0
Summary: Add your description here
Requires-Python: >=3.13.1
Requires-Dist: beautifulsoup4>=4.12.3
Requires-Dist: html2text>=2024.2.26
Requires-Dist: mcp[cli]>=1.9.1
Requires-Dist: requests>=2.32.3
